aws_sso_tool/__init__.py
aws_sso_tool/auth.py
aws_sso_tool/cli.py
aws_sso_tool/ec2_operations.py
aws_sso_tool/s3_operations.py
aws_sso_tool/utils.py
aws_sso_tool-0.1.14.dist-info/LICENSE
aws_sso_tool-0.1.14.dist-info/METADATA
aws_sso_tool-0.1.14.dist-info/WHEEL
aws_sso_tool-0.1.14.dist-info/entry_points.txt
aws_sso_tool-0.1.14.dist-info/top_level.txt
aws_sso_tool-0.1.14.dist-info/RECORD
