Metadata-Version: 2.1
Name: aws_sso_tool
Version: 0.1.14
Summary: CLI tool to simplify AWS SSO login and operations
Home-page: https://github.com/mosiko1234/aws_sso_tool
Author: Moshe Eliya
Author-email: mosiko1234@gmail.com
Classifier: Programming Language :: Python :: 3
Classifier: License :: OSI Approved :: MIT License
Classifier: Operating System :: OS Independent
Classifier: Development Status :: 3 - Alpha
Classifier: Intended Audience :: Developers
Classifier: Topic :: Software Development :: Libraries :: Python Modules
Requires-Python: >=3.6
License-File: LICENSE
Requires-Dist: boto3>=1.18.0
Requires-Dist: click>=7.0
